ndotel/NDspanProcessor.py
ndotel/__init__.py
ndotel/distro.py
ndotel/metric_exporter.py
ndotel/sampler.py
otel_custom_distro-0.1.0.dist-info/METADATA
otel_custom_distro-0.1.0.dist-info/WHEEL
otel_custom_distro-0.1.0.dist-info/entry_points.txt
otel_custom_distro-0.1.0.dist-info/top_level.txt
otel_custom_distro-0.1.0.dist-info/RECORD
